{"QroUad2UdZzG5hYHZTMQfg==":"twidgrid-96x96.png","nk5ln/fb3MBbYJFfiZcLmQ==":"twidgrid-512x512.png","ZoMzQ2tldlNrP4aw+YlbUw==":"loki.webp","vEonTHqRoYwgrY1K0CJqYQ==":"full%20house.webp","0n+J1lTHePyWhyrYWulWsg==":"for%20all%20mankind.webp","KQbp1t/GkgH4rkYTmefZpg==":"virgin%20river.webp","bRRivAmzgPGZK5GjvCnglw==":"invasion.webp","xwNZLmCzEHlaEDgoCDKB2A==":"lupin.webp","6TvDTHlSit5IzDFPSphYDA==":"movies-large-512x512.png","FNVXsuH+Sc4ERoWCCFBDhw==":"argylle.webp","l9zW7H4Tf/B4bd4N1H3sGA==":"madame%20web.webp","irOAabS8M1peSxdgINffwQ==":"the%20fall%20guy.webp","czWKbZwbZBnJ3q6iSaDfqw==":"dune%20part%20two.webp","wT9oLJ5wfg9Hq213jEUzkA==":"damsel.webp","Qchc0lw5/npYYcWmLEPvlg==":"ghostbusters%20frozen%20empire.webp","YNyv1DTYf0YM09nn0XGTqQ==":"music-large-512x512.png","Tz6gE9jDmjf/fwWXNjuzqA==":"ariana_grande_-_yes,_and-300x300.png","itaQ3XVgiu+/irqT9NOcWA==":"_lovin_on_me__by_jack_harlow_-_cover_art-316x316.png","q19O0DpQ6UnX+KVjrTX0JA==":"taylor_swift_-_cruel_summer-300x300.png","Ab3HC6euLQ354lXMQX0XNQ==":"tate_mcrae_-_greedy-300x300.png","AhHFvBbAMoRCxwzw4xy/vA==":"redrum-409x409.png","aJPhY1P/wzBcHeMeM/Nk8Q==":"zach_bryan_-_i_remember_everything-300x300.png","EXaFrGYKnjnf2dbLs+XStw==":"sports-large-512x512.png","QopfUnNP1l4eDp42OWTV6Q==":"uefa-400x400.jpg","VxdxjrHMAxSuGjKFy5ku8Q==":"fifa-400x400.jpg","9Kc+kp15xbXII+xmlWmGeA==":"live-stream-3-160x160.png","7NCxz3cGjL8HRNldVAWUvQ==":"beverly%20hills%20cop%20axel%20f-450x630.jpg","t4jOIFpengCXV82eSvwHpw==":"foundation.webp","99CbWwdsE4LhKYJMB+6hwQ==":"jessica%20frost.webp","2HGqZdDRVNG2Au8ZN3NAKA==":"kraven%20the%20hunter.webp","V6LGJ3vjFORovRzgLVPKqQ==":"borderlands.webp","VeaRcGvgOpYlezsQ500U2Q==":"deadpool%203.webp","8yUDZye5AizO8A4ewxZr5Q==":"inside%20out%202.webp","4BKOZI6rkbjN1Q+fuGed8A==":"furiosa%20a%20mad%20max%20saga.webp","nLMVHK+gc2hGmlecOWOIRQ==":"if.webp","u8kVU75OfhMG/nk5SADw9g==":"kalki%202898-ad-300x400.jpg","lrlLnsUo7LaWaaL96bEQHQ==":"kingdom%20of%20the%20planet%20of%20the%20apes.webp","RudwTegifXJMj/DPzHcgkw==":"civil%20war.webp","8KoqIdVLFpzQDbwnfJm5ew==":"rebel%20moon%20-%20part%20two%20the%20scargiver-1000x1400.jpg","0CJeqXUczQ45idNkw2LRsg==":"the%20beekeeper-1920x2560.jpg","XqStexa3ucYeWEdbgE9USg==":"background1.jpg","c8uW9Aqo5EjlClYpqdquag==":"aquaman%20and%20the%20lost%20kingdom-537x805.jpg","3dToNB4wPVWgfDuCsRspJg==":"napoleon-1000x1482.jpg","R3PvwBw8gVUhWhLthEG9OQ==":"the%20book%20of%20clarence-604x755.jpg","MRGh4rCktCjC88v1jMOSTQ==":"i.s.s.-300x434.jpg","J0fcECUEsHSLXrEUgmPVSw==":"the%20penguin-1000x1483.jpg","2XPn62Bb61fJgCr+0/jcDQ==":"skeleton%20crew-1000x1502.jpg","0jI0oD02O8/J6/kQ7AADwQ==":"we%20were%20tomorrow-1000x1428.jpg","/6PFI8FJ8rN4NKsrHaFrhg==":"fallout-1000x1481.jpg","RyCWZrGLFpzTso2ZFE5+GQ==":"3%20body%20problem-1000x1481.jpg","e9dNTbk3fPe4aTJldh+veA==":"death%20and%20other%20details-1000x1483.jpg","fAzinuylFRD2dNEOIV4iwA==":"boy%20swallows%20universe-1000x1538.jpg","ZtDB4hRZRAAYAMeushEzww==":"percy%20jackson%20and%20the%20olympians-1000x1250.jpg","qgY9sie9KW4Zt1E9MGnSaA==":"echo-1000x1481.jpg","NxiUDlv93fxlBtF/PUbKIQ==":"gen%20v-1000x1419.jpg","s6hIqp6OAQOhvuJG/y0rQw==":"ahsoka-184x273.jpg","xXtiPp1vbtlMpTZ47xz0Vg==":"secret%20invasion-1688x2500.jpg","8dyHcvUsAQMYekLmJpkWsw==":"based%20on%20a%20true%20story-1000x1481.jpg","qforNv0mGM1qgX3ILA51nw==":"silo-1000x1500.jpg","4P0E/FveSM073QYkB1eeMg==":"citadel-1000x1481.jpg","1x/sHpoq0B3K2Fb8QYmQaA==":"the%20power-537x796.jpg","bm2jbf5c90pJl1cQWqtF2Q==":"rabbit%20hole-240x370.jpg","rWrM04/s4QomaQpP8cDU8A==":"mrs.%20davis-1000x1481.jpg","nyjES7C0Q/36Zcc6rodf7A==":"hello%20tomorrow!-1000x1500.jpg","1+m0N6bTJ4UXLmEiavhjmw==":"the%20ark-1000x1333.jpg","ms8FpEoKzMrz0jrCzjrWJg==":"the%20last%20of%20us-1000x1481.jpg","wcgafIhYknKo3iNgQX3iEw==":"national%20treasure%20edge%20of%20history-1000x1242.jpg","OUONVJl8NULp9fjiINBBJA==":"willow-1000x1481.jpg","x3pMD8EAwi59rkrBTF8KYA==":"tulsa%20king-1000x1481.jpg","iPluxd81YvFfIR2NV13bXQ==":"the%20peripheral-1000x1778.jpg","9Gwq9q0EXVpT4HU9r6120Q==":"she-hulk%20attorney%20at%20law-1000x1481.jpg","DwYw266IWZTSxfsbZH0aSQ==":"the%20terminal%20list-1000x1250.jpg","zks3/67Uaq6nQxf2siGs3w==":"paper%20girls-1000x1505.jpg","j0eqrFYK4Sox2E53CNZHAQ==":"ms.%20marvel-1000x1480.jpg","Q6goXzD6uEU7A+XQikzYMg==":"moon%20knight-1000x1481.jpg","W5ncDZmBCA8LflMF7NjVbQ==":"the%20endgame-1000x1481.jpg","4rMkE2BKn1FmZKDyjFV7pQ==":"from-1944x2880.jpg","pQiDDrmlw4ow8DuLTE13iQ==":"severance-1000x1500.jpg","xsqRuVuBiEHSApwrr7a0PQ==":"suspicion-675x1000.jpg","7JkEjg0pELoSouEvvgFiDA==":"reacher-537x716.jpg","And8x+WP4OmgAngUTzNqdA==":"peacemaker-810x1200.jpg","W60AcmVTTHkRXkqs5lYUDA==":"naomi-1000x1250.jpg","3rdW3GNFsZenmPzmQqEbkg==":"the%20man%20who%20fell%20to%20earth-1000x1500.jpg","l5py0lNhyuWe74TGv1FRHA==":"station%20eleven-562x843.jpg","7+bo9hbNJIP6fl1JF7bHwQ==":"la%20brea-675x1000.jpg","Vx4+cmGdld4mw8X59xGijg==":"y%20the%20last%20man-1000x1250.jpg","2R5TN1cLSlo49wK8sKQcpQ==":"mr.%20&%20mrs.%20smith-537x671.jpg","vXIUSV4OA32GWz57SnhE3g==":"doja_cat_-_paint_the_town_red-220x220.png","l006fEuozE3gL4mDjzWC/A==":"lose%20control-640x640.jpg","HXHvjqv3FGIXsLo/4HHV2g==":"sza_-_snooze-220x220.png","whdQo2rqq6gFwd5HwlaV+A==":"2026%20fifa%20world%20cup-537x537.jpg","7qz2lOzKEMTdTz/nnwy/9Q==":"2022%20fifa%20world%20cup.webp","COWSMbBonbgp22tZLz3+Tg==":"2018-1200x800.jpeg","qIj6gXVgpgD6RH7tgrUqNQ==":"brasil-1657x932.jpeg","nwfgqgNILWRm5b6pMCuOWw==":"2010-537x537.png","2cLfjpENTz/BS1qNeNp26g==":"2006%20fifa%20world%20cup-480x360.jpeg","s0GPiq8wrbNywn5dtpzAcg==":"2002%20fifa%20world%20cup-500x500.jpg","pFjYyRCC417aGpUTAynujA==":"1998-france-world-cup-logo-537x537.jpg","B5S4oKQBGaopltHXTbtz5w==":"1994%20fifa%20world%20cup.webp","rQBoxtrZW2OSuI+gdTWK8g==":"italy-1990-world-cup-1000x1000.jpg","e83h+Z982QjuuA4GJTxuOw==":"1986%20fifa%20world%20cup-1000x1000.jpg","GjiGbZatV+Yo6sot41xhCw==":"1982%20fifa%20world%20cup-550x550.jpg","EnnAy8VkIaAzUcaKWUozqQ==":"1978%20fifa%20world%20cup-1000x750.jpeg","Y4XORFkCE0oZ3Qc5WOHssg==":"74-720x720.jpeg","b7zEDP2evp8s8YGon9pQwQ==":"mexico70-3307x3307.jpg","6WZj86VMsMJkDcryIfpizQ==":"world-cup-logo-1966.webp","AVmOfKLuqbDfRragtQLHqw==":"1962-300x300.jpg","4bagAb37hKLtZnj2iwS4oQ==":"1958-969x969.jpg","E5rKNz2bSwqftmewEcVinQ==":"1954-1-227x360.png","xZdROLF1heX9B2Wu10OYwQ==":"1950brazil-1000x1000.jpg","VKsiaGWO+enXl0zJBBGWbQ==":"1938france-537x537.jpg","y5kxyyp5yLnZPGfWUU1eWw==":"1934_fifa_worldcup_poster-606x606.jpg","/dewfC1cSkqBaukh0mlDxw==":"uruguay_1930_world_cup-606x606.jpg","63yyJAxtGe5lCbgGayP4vw==":"brazil-171x171.png","w+hu0SCjJSYaDMlZyR7Y2w==":"germany-171x171.png","TTmRqfkNRyYcV4E+tLhXpA==":"italy-171x171.png","wfHJOvQC/xc9yk9pVHnlNw==":"argentina-171x171.png","TIOoZMUbAHOV90rQA3e4Iw==":"france-171x171.png","PHwyDsrnpliVTL655Lu+gA==":"uruguay-171x171.png","H5nyU9eBSgvjPrKAeuvALA==":"england-171x171.png","cMXTLi1F+YfHrh5Jy3j57A==":"spain-171x171.png","7G8J6GzCMLU+Bk5wvnHYcA==":"agora%20hills-1000x1000.jpg","gDXGQZYgdQb3TKScHbzECQ==":"tyla_-_water-220x220.png","7gcqtTEy4R/jRPaaR0ZNYw==":"last%20night-300x300.png","jC1xx3Ur6/JqiFROAGcScg==":"thinkin'%20bout%20me-1000x1000.png","arfkd0srSYCXSwSbogqsOw==":"fast%20car-1000x1000.jpg","OeDkburEfemits0LquKjdg==":"noah_kahan_-_stick_season_(song)-220x220.png","yimRZqN2lM+WAnMv5Bycig==":"is%20it%20over-340x340.png","q3aOy3U4YIy9xLnn+gUehQ==":"what%20was%20i%20made%20for-220x220.png","bS6DujGOIRt9kbiT45L4lg==":"uefa-euro-2024-logo-376x275.jpeg","jS+f40Wt9BaTJUZ9IZ0qCg==":"2020.webp","bQNF0eCQmBVGvvv2O0LEuQ==":"2016france.webp","yjYaxaCuOIMnssnhVnzdXA==":"2016france-1.webp","HZTLqtZviztTzNyCFaEKbQ==":"euro-2012-logo-430x400.jpg","OTDY27WKHJv2U+poxk6p1Q==":"euro-2012-logo-430x400.jpeg","+dBSEluvelPuj2og0tGQzg==":"2008autchf-300x300.png","DV71oPKfXuShmlHm/Gng1w==":"2004portugal.gif","CoU3BrKcE0rMf8F6tDSucQ==":"uefa-euro-2000-1024x724.jpg","GcNM41xfhfyyt6hYWGtdgQ==":"uefa-euro-2000-1024x724.jpeg","8epDzZMYq26CEV324ekkng==":"1996-uefa-euro-96-800x800.jpg","R2G7VaCb04LFXt5NQ8KKAg==":"1992-uefa-european-football-championship6254-866x650.jpg","MSkKTmq9x2NXY37lNQu/3A==":"1992-uefa-european-football-championship6254-866x650.jpeg","Phjnddb/PKDXapCL0p+8lA==":"1988-uefa-european-football-championship3018-866x650.jpg","Tos7KyZ2jiLeN0dmYsJF9A==":"1988-uefa-european-football-championship3018-866x650.jpeg","uOhivO37a9JTjYNJ//Z9+Q==":"1984uefa-266x190.png","GLLImv43yC7tfsYJDaSzGw==":"1984uefa-1-266x190.png","5S2FA48uycV0EugyYtsr0Q==":"1980-uefa-european-football-championship5009-866x650.jpg","uWGaIzJWcQFUywYWlgTjzQ==":"1980-uefa-european-football-championship5009-866x650.jpeg","VTtKioQVg29KiPNOpRthSw==":"1976-uefa-european-football-championship3626-866x650.jpg","1qAeMUgPL3wVZAVIX8uK8g==":"1976-uefa-european-football-championship3626-866x650.jpeg","/sEF+CyFf9Ch2QmKb2pxLg==":"1972-uefa-european-football-championship9036-866x650.jpg","BWvWkgYKJT7R80WJa8sByw==":"1972-uefa-european-football-championship9036-866x650.jpeg","oq8tPr98YTi9E118Lr3sTw==":"1968-uefa-european-football-championship5107-866x650.jpg","GCenb75iL0FUi4BJ6mVijg==":"1968-uefa-european-football-championship5107-866x650.jpeg","cEdQK8ivy353HVzQw1W6ZQ==":"1964-european-nations-cup2660-520x390.jpg","X/vCw7weqlo0iuaaKtc/uA==":"1964-european-nations-cup2660-520x390.jpeg","IxAi1oFdY64iCtwvR/I1ng==":"1960-european-nations-cup4869-866x650.jpg","lhOXLbRi4J8JXa+egXNPjg==":"1960-european-nations-cup4869-866x650.jpeg","AaU187H8UmFso6Z9GPwuHA==":"portugal-192x192.png","UufgRvIHAlMhjyfhk/Qx1A==":"denmark-192x192.png","mfeaZJhHxcHJAgo+fHOjNg==":"netherlands-192x192.png","pNc39S9NRHz99ceOsHlM2Q==":"czech-republic-192x192.png","np1k2VwTxSyc8/UqJ7UVDw==":"greece-192x192.png","UGk4xllVrycRHeedDvX/LA==":"russia-192x192.png","AK8qPqr8BlywDF1EmAT9MA==":"white%20horse-340x340.jpg","S1kbVKxj0qqIVWjsMTzolw==":"rich%20baby%20daddy-340x340.jpg","BqDy7Ph2UqZBWmRy36aNVw==":"igual%20que%20un%20angel-340x340.png","FoIMXl7CJXQHOVmdC/QYrA==":"la%20diabla-340x340.png","1s/bDAOEwm3hKr/6qeHr8g==":"ftcu-340x340.jpg","MdybW3b12fffSKnOJcP1Ig==":"lil%20boo%20thang-340x340.png","28+uBRuLZ9EfNeG2h5GLAA==":"flowers-340x340.png","RSv6AheroaBCPCqIUvYCiA==":"everybody-340x340.png","XfLjzZHKe5ZLc+XD6TPFwQ==":"houdini-340x340.png","o7qgPRh5jbtqE2LQBxL+7g==":"world%20on%20fire-340x340.jpg","l2i8tMfXjylJAVJjs3nHpQ==":"search-512x512.png"}